[
  {
    "category": "SearchEngines",
    "title": "Look at this cool search engine",
    "link": "https://www.google.com/",
    "poster": "Jerry",
    "comments":
      [
        "dammit jerry",
        "wow Jerry, this is so interesting. Did you just find out about America as well?",
        "I heard that they mine your data. Good on them for finding a way to provide a service for free."
      ]
  },
  {
    "category": "Shopping",
    "title": "You can buy anything at this site! You should go buy stuff!",
    "link": "https://www.amazon.com",
    "poster": "Jeff Bezos",
    "comments":
      [
        "Even I think you're a nerd. -Bill Gates",
        "Blue Origin sucks. Start a real space company. -Elon Musk"
      ]
  },
  {
    "category": "Shopping",
    "title": "This is like Amazon but cheaper",
    "link": "https://www.aliexpress.com",
    "poster": "your mom",
    "comments":
      [
        "day 455 of waiting for my watch to be delivered: I wonder what time it is..."
      ]
  },
  {
    "category": "Wikis",
    "title": "This has helped me more than you can imagine",
    "link": "https://darksouls3.wiki.fextralife.com/Dark+Souls+3+Wiki",
    "poster": "High Lord Mayor of Anor Londo",
    "comments":
      [
        "Git Gud",
        "Git Gud",
        "Git Gud",
        "Git Gud",
        "Git Gud",
        "Git Gud",
        "Git Gud",
        "Git Gud",
        "Git Gud",
        "Git Gud"
      ]
  },
  {
    "category": "SocialMedia",
    "title": "Objectively the better social media",
    "link": "https://www.reddit.com",
    "poster": "everyone",
    "comments":
      [
        "use Pinterest like a real man"
      ]
  },
  {
    "category": "Entertainment",
    "title": "This site has hilarious skits. Gimme 7 dollars and you can visit it",
    "link": "https://doormonster.tv",
    "poster": "Extortionist Hobo",
    "comments":
      [
        ""
      ]
  },
  {
    "category": "",
    "title": "",
    "link": "",
    "poster": "",
    "comments":
      [
        "",
        "",
        ""
      ]
  }
]
